{
  "id": "1ab705eb-0cfb-4458-8527-563b702a9e8d",
  "prevId": "00000000-0000-0000-0000-000000000000",
  "version": "7",
  "dialect": "postgresql",
  "tables": {
    "public.product_images": {
      "name": "product_images",
      "schema": "",
      "columns": {
        "id": {
          "name": "id",
          "type": "serial",
          "primaryKey": true,
          "notNull": true
        },
        "product_id": {
          "name": "product_id",
          "type": "integer",
          "primaryKey": false,
          "notNull": true
        },
        "image_url": {
          "name": "image_url",
          "type": "text",
          "primaryKey": false,
          "notNull": true
        },
        "image_public_id": {
          "name": "image_public_id",
          "type": "text",
          "primaryKey": false,
          "notNull": true
        },
        "is_primary": {
          "name": "is_primary",
          "type": "boolean",
          "primaryKey": false,
          "notNull": true,
          "default": false
        },
        "order": {
          "name": "order",
          "type": "integer",
          "primaryKey": false,
          "notNull": true,
          "default": 0
        },
        "created_at": {
          "name": "created_at",
          "type": "timestamp",
          "primaryKey": false,
          "notNull": true,
          "default": "now()"
        }
      },
      "indexes": {
        "product_images_product_id_idx": {
          "name": "product_images_product_id_idx",
          "columns": [
            {
              "expression": "product_id",
              "isExpression": false,
              "asc": true,
              "nulls": "last"
            }
          ],
          "isUnique": false,
          "concurrently": false,
          "method": "btree",
          "with": {}
        }
      },
      "foreignKeys": {
        "product_images_product_id_products_id_fk": {
          "name": "product_images_product_id_products_id_fk",
          "tableFrom": "product_images",
          "tableTo": "products",
          "columnsFrom": [
            "product_id"
          ],
          "columnsTo": [
            "id"
          ],
          "onDelete": "cascade",
          "onUpdate": "no action"
        }
      },
      "compositePrimaryKeys": {},
      "uniqueConstraints": {},
      "policies": {},
      "checkConstraints": {},
      "isRLSEnabled": false
    },
    "public.products": {
      "name": "products",
      "schema": "",
      "columns": {
        "id": {
          "name": "id",
          "type": "serial",
          "primaryKey": true,
          "notNull": true
        },
        "name": {
          "name": "name",
          "type": "text",
          "primaryKey": false,
          "notNull": true
        },
        "barcode": {
          "name": "barcode",
          "type": "text",
          "primaryKey": false,
          "notNull": true
        },
        "price": {
          "name": "price",
          "type": "numeric(10, 2)",
          "primaryKey": false,
          "notNull": true
        },
        "description": {
          "name": "description",
          "type": "text",
          "primaryKey": false,
          "notNull": false
        },
        "category": {
          "name": "category",
          "type": "text",
          "primaryKey": false,
          "notNull": false
        },
        "stock_quantity": {
          "name": "stock_quantity",
          "type": "integer",
          "primaryKey": false,
          "notNull": true,
          "default": 0
        },
        "image_url": {
          "name": "image_url",
          "type": "text",
          "primaryKey": false,
          "notNull": false
        },
        "image_public_id": {
          "name": "image_public_id",
          "type": "text",
          "primaryKey": false,
          "notNull": false
        },
        "is_active": {
          "name": "is_active",
          "type": "boolean",
          "primaryKey": false,
          "notNull": true,
          "default": true
        },
        "created_at": {
          "name": "created_at",
          "type": "timestamp",
          "primaryKey": false,
          "notNull": true,
          "default": "now()"
        },
        "updated_at": {
          "name": "updated_at",
          "type": "timestamp",
          "primaryKey": false,
          "notNull": true,
          "default": "now()"
        }
      },
      "indexes": {
        "barcode_idx": {
          "name": "barcode_idx",
          "columns": [
            {
              "expression": "barcode",
              "isExpression": false,
              "asc": true,
              "nulls": "last"
            }
          ],
          "isUnique": false,
          "concurrently": false,
          "method": "btree",
          "with": {}
        },
        "category_idx": {
          "name": "category_idx",
          "columns": [
            {
              "expression": "category",
              "isExpression": false,
              "asc": true,
              "nulls": "last"
            }
          ],
          "isUnique": false,
          "concurrently": false,
          "method": "btree",
          "with": {}
        }
      },
      "foreignKeys": {},
      "compositePrimaryKeys": {},
      "uniqueConstraints": {
        "products_barcode_unique": {
          "name": "products_barcode_unique",
          "nullsNotDistinct": false,
          "columns": [
            "barcode"
          ]
        }
      },
      "policies": {},
      "checkConstraints": {},
      "isRLSEnabled": false
    }
  },
  "enums": {},
  "schemas": {},
  "sequences": {},
  "roles": {},
  "policies": {},
  "views": {},
  "_meta": {
    "columns": {},
    "schemas": {},
    "tables": {}
  }
}